Workbook
Name SlicerCache_Table_1_Col_2: #N/A
Name SlicerCache_Table_1_Col_3: #N/A

Sheet Ingresos y Gastos
A1: Fecha | B1: Trimestre | C1: Semestre | D1: Tipo | E1: Categoría | F1: Sub-categoría | G1: Monto
A2: 44927 | B2: =+CONCATENATE("T",ROUNDUP(MONTH(A2)/3,0)) -> T1 | C2: =+CONCATENATE("Sem"," ",ROUNDUP(MONTH(A2)/6,0)) -> Sem 1 | D2: Gastos | E2: Hogar | F2: Comida | G2: 88
A3: 44927 | B3: =+CONCATENATE("T",ROUNDUP(MONTH(A3)/3,0)) -> T1 | C3: =+CONCATENATE("Sem"," ",ROUNDUP(MONTH(A3)/6,0)) -> Sem 1 | D3: Gastos | E3: Hogar | F3: Comida | G3: 152
A4: 44927 | B4: =+CONCATENATE("T",ROUNDUP(MONTH(A4)/3,0)) -> T1 | C4: =+CONCATENATE("Sem"," ",ROUNDUP(MONTH(A4)/6,0)) -> Sem 1 | D4: Gastos | E4: Personal | F4: Educación | G4: 171
A5: 44927 | B5: =+CONCATENATE("T",ROUNDUP(MONTH(A5)/3,0)) -> T1 | C5: =+CONCATENATE("Sem"," ",ROUNDUP(MONTH(A5)/6,0)) -> Sem 1 | D5: Gastos | E5: Personal | F5: Ropa | G5: 99
A6: 44927 | B6: =+CONCATENATE("T",ROUNDUP(MONTH(A6)/3,0)) -> T1 | C6: =+CONCATENATE("Sem"," ",ROUNDUP(MONTH(A6)/6,0)) -> Sem 1 | D6: Gastos | E6: Transporte | F6: Mantenimiento | G6: 67
A7: 44929 | B7: =+CONCATENATE("T",ROUNDUP(MONTH(A7)/3,0)) -> T1 | C7: =+CONCATENATE("Sem"," ",ROUNDUP(MONTH(A7)/6,0)) -> Sem 1 | D7: Gastos | E7: Entretenimiento | F7: Viaje | G7: 20
A8: 44929 | B8: =+CONCATENATE("T",ROUNDUP(MONTH(A8)/3,0)) -> T1 | C8: =+CONCATENATE("Sem"," ",ROUNDUP(MONTH(A8)/6,0)) -> Sem 1 | D8: Gastos | E8: Transporte | F8: Peaje | G8: 20
A9: 44930 | B9: =+CONCATENATE("T",ROUNDUP(MONTH(A9)/3,0)) -> T1 | C9: =+CONCATENATE("Sem"," ",ROUNDUP(MONTH(A9)/6,0)) -> Sem 1 | D9: Gastos | E9: Transporte | F9: Estacionamiento | G9: 26
A10: 44930 | B10: =+CONCATENATE("T",ROUNDUP(MONTH(A10)/3,0)) -> T1 | C10: =+CONCATENATE("Sem"," ",ROUNDUP(MONTH(A10)/6,0)) -> Sem 1 | D10: Gastos | E10: Transporte | F10: Mantenimiento | G10: 31
A11: 44931 | B11: =+CONCATENATE("T",ROUNDUP(MONTH(A11)/3,0)) -> T1 | C11: =+CONCATENATE("Sem"," ",ROUNDUP(MONTH(A11)/6,0)) -> Sem 1 | D11: Gastos | E11: Mascotas | F11: Comida de Mascota | G11: 52
A12: 44931 | B12: =+CONCATENATE("T",ROUNDUP(MONTH(A12)/3,0)) -> T1 | C12: =+CONCATENATE("Sem"," ",ROUNDUP(MONTH(A12)/6,0)) -> Sem 1 | D12: Gastos | E12: Hogar | F12: Comida | G12: 37
A13: 44933 | B13: =+CONCATENATE("T",ROUNDUP(MONTH(A13)/3,0)) -> T1 | C13: =+CONCATENATE("Sem"," ",ROUNDUP(MONTH(A13)/6,0)) -> Sem 1 | D13: Gastos | E13: Personal | F13: Educación | G13: 125
... A563: 45291 | B563: =+CONCATENATE("T",ROUNDUP(MONTH(A563)/3,0)) -> T4 | C563: =+CONCATENATE("Sem"," ",ROUNDUP(MONTH(A563)/6,0)) -> Sem 2 | D563: Gastos | E563: Entretenimiento | F563: Suscripción de streaming | G563: 50

Sheet Meta - Ingresos y Ahorro 
A1: Mes | B1: Meta de Ingresos | C1: Meta de Ahorro
A2: Enero | B2: 5000 | C2: 209
A3: Febrero | B3: 5000 | C3: 209
A4: Marzo | B4: 5500 | C4: 209
A5: Abril | B5: 6000 | C5: 209
A6: Mayo | B6: 6500 | C6: 209
A7: Junio | B7: 5000 | C7: 209
A8: Julio | B8: 4000 | C8: 209
A9: Agosto | B9: 5000 | C9: 209
A10: Septiembre | B10: 4500 | C10: 209
A11: Octubre | B11: 5500 | C11: 209
A12: Noviembre | B12: 6000 | C12: 209
A13: Diciembre | B13: 6500 | C13: 209

Sheet Análisis y Panel
T5: Gasto Mensual | W5: Saldo Mensual antes del Ahorro | AD5: Ingresos vs Meta | AK5: Ahorro Mensual | AU5: Principales Gastos | AY5: Ingresos | BB5: Gastos
AG7: Mes | AH7: Ingresos | AI7: Meta de Ingresos
AA8: Mes | AB8: Saldo | AG8: =AD8 -> ene | AH8: =AE8 -> 4500 | AI8: ='Meta - Ingresos y Ahorro '!B2 -> 5000 | AO8: Mes | AP8: Saldo | AR8: Mes | AS8: Ahorro
AA9: =W9 -> ene | AB9: =Y9-X9 -> -155 | AG9: =AD9 -> feb | AH9: =AE9 -> 5000 | AI9: ='Meta - Ingresos y Ahorro '!B3 -> 5000 | AO9: =AK9 -> ene | AP9: =AM9-AL9 -> -155 | AR9: =AO9 -> ene | AS9: =IF(AP9<=-1,AP9*0,AP9*20%) -> 0
AA10: =W10 -> feb | AB10: =Y10-X10 -> 558 | AG10: =AD10 -> mar | AH10: =AE10 -> 5500 | AI10: ='Meta - Ingresos y Ahorro '!B4 -> 5500 | AO10: =AK10 -> feb | AP10: =AM10-AL10 -> 558 | AR10: =AO10 -> feb | AS10: =IF(AP10<=-1,AP10*0,AP10*20%) -> 111.6
AA11: =W11 -> mar | AB11: =Y11-X11 -> 2065 | AG11: =AD11 -> abr | AH11: =AE11 -> 6000 | AI11: ='Meta - Ingresos y Ahorro '!B5 -> 6000 | AO11: =AK11 -> mar | AP11: =AM11-AL11 -> 2065 | AR11: =AO11 -> mar | AS11: =IF(AP11<=-1,AP11*0,AP11*20%) -> 413 | AZ11: Saldo antes del Ahorro | BA11: =AY8-BB8 -> 1742
AA12: =W12 -> abr | AB12: =Y12-X12 -> 1616 | AG12: =AD12 -> may | AH12: =AE12 -> 5700 | AI12: ='Meta - Ingresos y Ahorro '!B6 -> 6500 | AO12: =AK12 -> abr | AP12: =AM12-AL12 -> 1616 | AR12: =AO12 -> abr | AS12: =IF(AP12<=-1,AP12*0,AP12*20%) -> 323.2 | AZ12: Ahorro | BA12: =AS22 -> 1228.4
AA13: =W13 -> may | AB13: =Y13-X13 -> -256 | AG13: =AD13 -> jun | AH13: =AE13 -> 5000 | AI13: ='Meta - Ingresos y Ahorro '!B7 -> 5000 | AO13: =AK13 -> may | AP13: =AM13-AL13 -> -256 | AR13: =AO13 -> may | AS13: =IF(AP13<=-1,AP13*0,AP13*20%) -> 0 | AZ13: Saldo Disponible | BA13: =BA11-BA12 -> 513.6
AA14: =W14 -> jun | AB14: =Y14-X14 -> 545 | AG14: =AD14 -> jul | AH14: =AE14 -> 6200 | AI14: ='Meta - Ingresos y Ahorro '!B8 -> 4000 | AO14: =AK14 -> jun | AP14: =AM14-AL14 -> 545 | AR14: =AO14 -> jun | AS14: =IF(AP14<=-1,AP14*0,AP14*20%) -> 109
AA15: =W15 -> jul | AB15: =Y15-X15 -> -92 | AG15: =AD15 -> ago | AH15: =AE15 -> 4500 | AI15: ='Meta - Ingresos y Ahorro '!B9 -> 5000 | AO15: =AK15 -> jul | AP15: =AM15-AL15 -> -92 | AR15: =AO15 -> jul | AS15: =IF(AP15<=-1,AP15*0,AP15*20%) -> 0
AA16: =W16 -> ago | AB16: =Y16-X16 -> -926 | AG16: =AD16 -> sept | AH16: =AE16 -> 5500 | AI16: ='Meta - Ingresos y Ahorro '!B10 -> 4500 | AO16: =AK16 -> ago | AP16: =AM16-AL16 -> -926 | AR16: =AO16 -> ago | AS16: =IF(AP16<=-1,AP16*0,AP16*20%) -> 0
AA17: =W17 -> sept | AB17: =Y17-X17 -> 1358 | AG17: =AD17 -> oct | AH17: =AE17 -> 4900 | AI17: ='Meta - Ingresos y Ahorro '!B11 -> 5500 | AO17: =AK17 -> sept | AP17: =AM17-AL17 -> 1358 | AR17: =AO17 -> sept | AS17: =IF(AP17<=-1,AP17*0,AP17*20%) -> 271.6
AA18: =W18 -> oct | AB18: =Y18-X18 -> -1727 | AG18: =AD18 -> nov | AH18: =AE18 -> 4500 | AI18: ='Meta - Ingresos y Ahorro '!B12 -> 6000 | AO18: =AK18 -> oct | AP18: =AM18-AL18 -> -1727 | AR18: =AO18 -> oct | AS18: =IF(AP18<=-1,AP18*0,AP18*20%) -> 0
AA19: =W19 -> nov | AB19: =Y19-X19 -> -999 | AG19: =AD19 -> dic | AH19: =AE19 -> 6500 | AI19: ='Meta - Ingresos y Ahorro '!B13 -> 6500 | AO19: =AK19 -> nov | AP19: =AM19-AL19 -> -999 | AR19: =AO19 -> nov | AS19: =IF(AP19<=-1,AP19*0,AP19*20%) -> 0
AA20: =W20 -> dic | AB20: =Y20-X20 -> -245 | AO20: =AK20 -> dic | AP20: =AM20-AL20 -> -245 | AR20: =AO20 -> dic | AS20: =IF(AP20<=-1,AP20*0,AP20*20%) -> 0
AG21: Suma Total | AH21: =SUM(AH8:AH19) -> 63800 | AI21: =SUM(AI8:AI19) -> 64500
AR22: Suma Ahorro | AS22: =SUM(AS9:AS20) -> 1228.4
AG23: Var. | AH23: =(AH21/AI21)-1 -> -0.010852713 | AR23: Suma Meta de Ahorro | AS23: =SUM(Saldo_Ahorro[Meta de Ahorro]) -> 2508
AR25: Var | AS25: =(AS22/AS23)-1 -> -0.51020734

Sheet Recursos
